OrthoBase/Projectors.py
OrthoBase/YoungTools.py
OrthoBase/__init__.py
OrthoBase/utils.py
OrthoBase/FORMData/SUn.prc
OrthoBase/FORMData/footer_new.frm
OrthoBase/FORMData/footer_old.frm
OrthoBase/FORMData/header.frm
OrthoBase/FORMData/symmetryzer.frm
OrthoBase-0.1.dist-info/LICENSE
OrthoBase-0.1.dist-info/METADATA
OrthoBase-0.1.dist-info/WHEEL
OrthoBase-0.1.dist-info/top_level.txt
OrthoBase-0.1.dist-info/RECORD
