Metadata-Version: 2.1
Name: OrthoBase
Version: 0.1
Summary: A module to perform the multiplet decomposition using Young tables and construct the corresponding projectors
Author-email: Bakar Chargeishvili <bakar.chargeishvili@desy.de>
Project-URL: Homepage, https://github.com/rakab/OrthoBase
Project-URL: Issues, https://github.com/rakab/OrthoBase/issues
Classifier: License :: OSI Approved :: BSD License
Classifier: Operating System :: OS Independent
Classifier: Natural Language :: English
Classifier: Programming Language :: Python :: 3
Classifier: Topic :: Scientific/Engineering :: Physics
Requires-Python: >=3.10
License-File: LICENSE
Requires-Dist: z3-solver
Requires-Dist: mpi4py
